roothazardlib/__init__.py
roothazardlib/configs/__init__.py
roothazardlib/configs/secure_client_service.py
roothazardlib/configs/yaml_config_singletone.py
roothazardlib-1.7.dist-info/METADATA
roothazardlib-1.7.dist-info/WHEEL
roothazardlib-1.7.dist-info/top_level.txt
roothazardlib-1.7.dist-info/RECORD
