Metadata-Version: 2.1
Name: roothazardlib
Version: 1.7
Summary: Development tools
Home-page: https://github.com/dkushche/RHLib_Python3
Author: roothazard
Requires-Python: >=3.10
Requires-Dist: pydantic >=2.5.3
Requires-Dist: PyYAML >=6.0.0
